_HyPhy.cpython-35m-darwin.so
HyPhy/__init__.py
hyphy_python-0.1.5.dist-info/DESCRIPTION.rst
hyphy_python-0.1.5.dist-info/METADATA
hyphy_python-0.1.5.dist-info/RECORD
hyphy_python-0.1.5.dist-info/WHEEL
hyphy_python-0.1.5.dist-info/metadata.json
hyphy_python-0.1.5.dist-info/top_level.txt
