Metadata-Version: 2.0
Name: hyphy-python
Version: 0.1.5
Summary: HyPhy package interface library
Home-page: http://github.com/veg/hyphy
Author: Sergei L Kosakovsky Pond and Steven Weaver
Author-email: spond@temple.edu
License: UNKNOWN
Platform: UNKNOWN
